gwyfile/__init__.py
gwyfile/_version.py
gwyfile/objects.py
gwyfile/util.py
pycroscopy_gwyfile-1.0.2.dist-info/licenses/LICENSE.rst
pycroscopy_gwyfile-1.0.2.dist-info/METADATA
pycroscopy_gwyfile-1.0.2.dist-info/WHEEL
pycroscopy_gwyfile-1.0.2.dist-info/top_level.txt
pycroscopy_gwyfile-1.0.2.dist-info/RECORD
