Metadata-Version: 2.4
Name: pycroscopy-gwyfile
Version: 1.0.2
Summary: Pure Python implementation of the Gwyddion file format
Home-page: https://github.com/tuxu/gwyfile
Author: Tino Wagner
Author-email: ich@tinowagner.com
License: MIT
Keywords: gwyddion file format
Platform: any
Classifier: Development Status :: 4 - Beta
Classifier: Environment :: Console
Classifier: Intended Audience :: Developers
Classifier: Intended Audience :: Science/Research
Classifier: License :: OSI Approved :: MIT License
Classifier: Operating System :: OS Independent
Classifier: Programming Language :: Python :: 2
Classifier: Programming Language :: Python :: 3
Classifier: Topic :: Scientific/Engineering
License-File: LICENSE.rst
Requires-Dist: numpy
Requires-Dist: six
Dynamic: author
Dynamic: author-email
Dynamic: classifier
Dynamic: description
Dynamic: home-page
Dynamic: keywords
Dynamic: license
Dynamic: license-file
Dynamic: platform
Dynamic: requires-dist
Dynamic: summary
